aroadtools/__init__.py
aroadtools/_version.py
aroadtools/roadlib/__init__.py
aroadtools/roadlib/auth.py
aroadtools/roadlib/constants.py
aroadtools/roadlib/deviceauth.py
aroadtools/roadlib/reqproxy.py
aroadtools/roadlib/utils.py
aroadtools/roadlib/database/__init__.py
aroadtools/roadlib/database/dbgen.py
aroadtools/roadlib/database/metadef/__init__.py
aroadtools/roadlib/database/metadef/basetypes.py
aroadtools/roadlib/database/metadef/complextypes.py
aroadtools/roadlib/database/metadef/database.py
aroadtools/roadlib/database/metadef/entitytypes.py
aroadtools/roadrecon/__init__.py
aroadtools/roadrecon/gather.py
aroadtools/roadrecon/plugins/__init__.py
aroadtools/roadrecon/plugins/policies.py
aroadtools/roadrecon/plugins/xlsexport.py
aroadtools/roadrecon/plugins/server/__init__.py
aroadtools/roadrecon/plugins/server/schema.py
aroadtools-0.0.1.dist-info/LICENSE
aroadtools-0.0.1.dist-info/METADATA
aroadtools-0.0.1.dist-info/WHEEL
aroadtools-0.0.1.dist-info/entry_points.txt
aroadtools-0.0.1.dist-info/top_level.txt
aroadtools-0.0.1.dist-info/zip-safe
aroadtools-0.0.1.dist-info/RECORD
