Metadata-Version: 2.1
Name: aroadtools
Version: 0.0.1
Summary: UNKNOWN
Home-page: https://github.com/skelsec/aroadtools
Author: Tamas Jos
Author-email: info@skelsecprojects.com
License: UNKNOWN
Platform: UNKNOWN
Classifier: Programming Language :: Python :: 3.6
Classifier: License :: OSI Approved :: MIT License
Classifier: Operating System :: OS Independent
Requires-Python: >=3.6
License-File: LICENSE
Requires-Dist: aiohttp
Requires-Dist: asn1crypto
Requires-Dist: cryptography
Requires-Dist: jwt
Requires-Dist: sqlalchemy
